{
  "gitSyncId": "68a3276fd0b8bb03282a0ce8_eebf8830-648f-49ef-99e1-139343f412ca",
  "id": "Home_Utils.getGendersFromTable",
  "pluginId": "js-plugin",
  "pluginType": "JS",
  "unpublishedAction": {
    "actionConfiguration": {
      "encodeParamsToggle": true,
      "jsArguments": [],
      "paginationType": "NONE",
      "timeoutInMillisecond": 10000
    },
    "collectionId": "Home_Utils",
    "confirmBeforeExecute": false,
    "datasource": {
      "isAutoGenerated": false,
      "name": "UNUSED_DATASOURCE",
      "pluginId": "js-plugin"
    },
    "dynamicBindingPathList": [
      {
        "key": "body"
      }
    ],
    "fullyQualifiedName": "Utils.getGendersFromTable",
    "name": "getGendersFromTable",
    "pageId": "Home",
    "runBehaviour": "MANUAL",
    "userSetOnLoad": false
  }
}